compile_commands/__init__.py
compile_commands/golden_test.py
compile_commands/main.py
compile_commands/test_cli.py
compile_commands/test_compile_commands.py
compile_commands-2.0.0.dist-info/LICENSE
compile_commands-2.0.0.dist-info/METADATA
compile_commands-2.0.0.dist-info/WHEEL
compile_commands-2.0.0.dist-info/entry_points.txt
compile_commands-2.0.0.dist-info/top_level.txt
compile_commands-2.0.0.dist-info/RECORD
