Metadata-Version: 2.1
Name: compile-commands
Version: 2.0.0
Summary: Compilation Database Manipulation Utility
Home-page: https://github.com/qdewaghe/compile-commands
Author: Quentin Dewaghe
Author-email: q.dewaghe@gmail.com
License: MIT
Platform: UNKNOWN
Classifier: Programming Language :: Python :: 3
Classifier: Programming Language :: Python :: 3.8
Classifier: Programming Language :: Python :: 3.9
Classifier: Programming Language :: Python :: 3.10
Classifier: License :: OSI Approved :: MIT License
Classifier: Operating System :: POSIX :: Linux
Classifier: Natural Language :: English
License-File: LICENSE
Requires-Dist: glob2
Requires-Dist: python-version (>="3.8")
Provides-Extra: extra
Requires-Dist: pytest ; extra == 'extra'
Requires-Dist: pytest-cov ; extra == 'extra'
Requires-Dist: mypy ; extra == 'extra'
Requires-Dist: gprof2dot ; extra == 'extra'
